pylsr/__init__.py
pylsr-2024.dist-info/LICENSE.md
pylsr-2024.dist-info/METADATA
pylsr-2024.dist-info/WHEEL
pylsr-2024.dist-info/RECORD
